nictools/CalTempFromBias.py
nictools/SP_FirstDerivatives.py
nictools/SP_LICENSE
nictools/SP_LeastSquares.py
nictools/__init__.py
nictools/finesky.py
nictools/fsutil.py
nictools/makemedmask.py
nictools/nic_rem_persist.py
nictools/opusutil.py
nictools/persutil.py
nictools/puftcorr.py
nictools/readTDD.py
nictools/rnlincor.py
nictools/saaclean.py
nictools/tfbutil.py
nictools-1.1.5.dist-info/LICENSE.txt
nictools-1.1.5.dist-info/METADATA
nictools-1.1.5.dist-info/WHEEL
nictools-1.1.5.dist-info/top_level.txt
nictools-1.1.5.dist-info/RECORD
