Metadata-Version: 2.1
Name: nictools
Version: 1.1.5
Summary: Python Tools for NICMOS Data
Home-page: https://github.com/spacetelescope/nictools
Author: Vicki Laidler, David Grumm
Author-email: help@stsci.edu
License: UNKNOWN
Platform: UNKNOWN
Classifier: Intended Audience :: Science/Research
Classifier: License :: OSI Approved :: BSD License
Classifier: Operating System :: OS Independent
Classifier: Programming Language :: Python
Classifier: Topic :: Scientific/Engineering :: Astronomy
Classifier: Topic :: Software Development :: Libraries :: Python Modules
Requires-Dist: astropy (>=1.0)
Requires-Dist: numpy (>=1.9)
Requires-Dist: scipy (>=0.16)
Requires-Dist: stsci.imagestats
Requires-Dist: stsci.tools
Provides-Extra: docs
Requires-Dist: sphinx ; extra == 'docs'
Requires-Dist: numpydoc ; extra == 'docs'
